kboat/__init__.py
kboat-0.0.2.dist-info/METADATA
kboat-0.0.2.dist-info/WHEEL
kboat-0.0.2.dist-info/top_level.txt
kboat-0.0.2.dist-info/RECORD
